pywright_gpt_tts/__init__.py
pywright_gpt_tts-0.0.5.dist-info/METADATA
pywright_gpt_tts-0.0.5.dist-info/WHEEL
pywright_gpt_tts-0.0.5.dist-info/top_level.txt
pywright_gpt_tts-0.0.5.dist-info/RECORD
