Metadata-Version: 2.4
Name: pywright-gpt-tts
Version: 0.0.5
Summary: Python Module for Free ChatGPT TTS
Author-email: Abdullah Al Jaber <abdullah.0.al.0.jaber@gmail.com>
Project-URL: Source Code, https://github.com/abdullah-al-jaber/pywright-gpt-tts
Requires-Python: >=3.10
